befehl/__init__.py
befehl/argument.py
befehl/command.py
befehl/common.py
befehl/option.py
befehl/parser.py
befehl-0.1.2.dist-info/licenses/LICENSE
befehl-0.1.2.dist-info/METADATA
befehl-0.1.2.dist-info/WHEEL
befehl-0.1.2.dist-info/top_level.txt
befehl-0.1.2.dist-info/RECORD
