Metadata-Version: 2.4
Name: befehl
Version: 0.1.2
Summary: a declarative, modular, lightweight, and versatile python library for building cli applications
Home-page: https://pypi.org/project/befehl/
Author: Steffen Richters-Finger
Author-email: srichters@uni-muenster.de
License: MIT
Project-URL: Source, https://github.com/RichtersFinger/befehl
Classifier: Development Status :: 5 - Production/Stable
Classifier: Intended Audience :: Developers
Classifier: Topic :: Software Development :: Libraries
Classifier: License :: OSI Approved :: MIT License
Classifier: Programming Language :: Python :: 3
Classifier: Programming Language :: Python :: 3.10
Classifier: Programming Language :: Python :: 3.11
Classifier: Programming Language :: Python :: 3.12
Requires-Python: >=3.10
License-File: LICENSE
Dynamic: author
Dynamic: author-email
Dynamic: classifier
Dynamic: description
Dynamic: description-content-type
Dynamic: home-page
Dynamic: license
Dynamic: license-file
Dynamic: project-url
Dynamic: requires-python
Dynamic: summary
